[
  {
    "id": 1,
    "nrp": "7025241001",
    "nama": "Achmad Bisri",
    "ck_hadir": true,
    "ck_dilibatkan": true,
    "jumlah_terpilih": 0,
    "jumlah_menjawab": 0,
    "jumlah_jawaban_benar": 0
  },
  {
    "id": 2,
    "nrp": "7025241002",
    "nama": "Windi Eka Yulia Retnani",
    "ck_hadir": true,
    "ck_dilibatkan": true,
    "jumlah_terpilih": 0,
    "jumlah_menjawab": 0,
    "jumlah_jawaban_benar": 0
  },
  {
    "id": 3,
    "nrp": "7025241003",
    "nama": "Erwin Duadja Betha Sasana",
    "ck_hadir": true,
    "ck_dilibatkan": true,
    "jumlah_terpilih": 0,
    "jumlah_menjawab": 0,
    "jumlah_jawaban_benar": 0
  },
  {
    "id": 4,
    "nrp": "7025241004",
    "nama": "Rony Wijanarko",
    "ck_hadir": true,
    "ck_dilibatkan": true,
    "jumlah_terpilih": 0,
    "jumlah_menjawab": 0,
    "jumlah_jawaban_benar": 0
  },
  {
    "id": 5,
    "nrp": "7025241005",
    "nama": "Doni Setio Pambudi",
    "ck_hadir": true,
    "ck_dilibatkan": true,
    "jumlah_terpilih": 0,
    "jumlah_menjawab": 0,
    "jumlah_jawaban_benar": 0
  },
  {
    "id": 6,
    "nrp": "7025241006",
    "nama": "Agung Mustika Rizki",
    "ck_hadir": true,
    "ck_dilibatkan": true,
    "jumlah_terpilih": 0,
    "jumlah_menjawab": 0,
    "jumlah_jawaban_benar": 0
  },
  {
    "id": 7,
    "nrp": "7025241007",
    "nama": "Januar Adi Putra",
    "ck_hadir": true,
    "ck_dilibatkan": true,
    "jumlah_terpilih": 0,
    "jumlah_menjawab": 0,
    "jumlah_jawaban_benar": 0
  },
  {
    "id": 8,
    "nrp": "7025241008",
    "nama": "Yunita Ardilla",
    "ck_hadir": true,
    "ck_dilibatkan": true,
    "jumlah_terpilih": 0,
    "jumlah_menjawab": 0,
    "jumlah_jawaban_benar": 0
  },
  {
    "id": 9,
    "nrp": "7025241009",
    "nama": "Setiawan Budiman",
    "ck_hadir": true,
    "ck_dilibatkan": true,
    "jumlah_terpilih": 0,
    "jumlah_menjawab": 0,
    "jumlah_jawaban_benar": 0
  },
  {
    "id": 10,
    "nrp": "7025241010",
    "nama": "Iska Yanuartanti",
    "ck_hadir": true,
    "ck_dilibatkan": true,
    "jumlah_terpilih": 0,
    "jumlah_menjawab": 0,
    "jumlah_jawaban_benar": 0
  },
  {
    "id": 11,
    "nrp": "7025241011",
    "nama": "Agus Muliantara",
    "ck_hadir": true,
    "ck_dilibatkan": true,
    "jumlah_terpilih": 0,
    "jumlah_menjawab": 0,
    "jumlah_jawaban_benar": 0
  },
  {
    "id": 12,
    "nrp": "7025241012",
    "nama": "Andy Rachman",
    "ck_hadir": true,
    "ck_dilibatkan": true,
    "jumlah_terpilih": 0,
    "jumlah_menjawab": 0,
    "jumlah_jawaban_benar": 0
  },
  {
    "id": 13,
    "nrp": "7025242013",
    "nama": "Rizqy Ahsana Putri",
    "ck_hadir": true,
    "ck_dilibatkan": true,
    "jumlah_terpilih": 0,
    "jumlah_menjawab": 0,
    "jumlah_jawaban_benar": 0
  },
  {
    "id": 14,
    "nrp": "7025241014",
    "nama": "I Komang Ari Mogi",
    "ck_hadir": true,
    "ck_dilibatkan": true,
    "jumlah_terpilih": 0,
    "jumlah_menjawab": 0,
    "jumlah_jawaban_benar": 0
  },
  {
    "id": 15,
    "nrp": "7025241015",
    "nama": "Ach. Arif Alfin",
    "ck_hadir": true,
    "ck_dilibatkan": true,
    "jumlah_terpilih": 0,
    "jumlah_menjawab": 0,
    "jumlah_jawaban_benar": 0
  },
  {
    "id": 16,
    "nrp": "7025241016",
    "nama": "Dava Aulia",
    "ck_hadir": true,
    "ck_dilibatkan": true,
    "jumlah_terpilih": 0,
    "jumlah_menjawab": 0,
    "jumlah_jawaban_benar": 0
  },
  {
    "id": 17,
    "nrp": "7025241017",
    "nama": "Imam Kuswardayan",
    "ck_hadir": true,
    "ck_dilibatkan": true,
    "jumlah_terpilih": 0,
    "jumlah_menjawab": 0,
    "jumlah_jawaban_benar": 0
  },
  {
    "id": 18,
    "nrp": "7025241018",
    "nama": "Moh. Muzayyin Amrulloh",
    "ck_hadir": true,
    "ck_dilibatkan": true,
    "jumlah_terpilih": 0,
    "jumlah_menjawab": 0,
    "jumlah_jawaban_benar": 0
  },	
  {
    "id": 19,
    "nrp": "7025241019",
    "nama": "Edi Junaedi",
    "ck_hadir": true,
    "ck_dilibatkan": true,
    "jumlah_terpilih": 0,
    "jumlah_menjawab": 0,
    "jumlah_jawaban_benar": 0
  },
  {
    "id": 20,
    "nrp": "7025241020",
    "nama": "Amirullah",
    "ck_hadir": true,
    "ck_dilibatkan": true,
    "jumlah_terpilih": 0,
    "jumlah_menjawab": 0,
    "jumlah_jawaban_benar": 0
  },
  {
    "id": 21,
    "nrp": "7025241021",
    "nama": "Fahmi Syuhada",
    "ck_hadir": true,
    "ck_dilibatkan": true,
    "jumlah_terpilih": 0,
    "jumlah_menjawab": 0,
    "jumlah_jawaban_benar": 0
  }
]